{
  "studies": [
    {
      "name": "Default Weekly Study for Adults",
      "name_short": "default",
      "description": "Default Study for Adults at KI, filled out by themselves",
      "day_labels": [
        {
          "name": "monday",
          "display_order": 0,
          "display_names": {
            "en": "Monday",
            "sv": "Måndag",
            "de": "Montag"
          }
        },
        {
          "name": "tuesday",
          "display_order": 1,
          "display_names": {
            "en": "Tuesday",
            "sv": "Tisdag",
            "de": "Dienstag"
          }
        },
        {
          "name": "wednesday",
          "display_order": 2,
          "display_names": {
            "en": "Wednesday",
            "sv": "Onsdag",
            "de": "Mittwoch"
          }
        },
        {
          "name": "thursday",
          "display_order": 3,
          "display_names": {
            "en": "Thursday",
            "sv": "Torsdag",
            "de": "Donnerstag"
          }
        },
        {
          "name": "friday",
          "display_order": 4,
          "display_names": {
            "en": "Friday",
            "sv": "Fredag",
            "de": "Freitag"
          }
        },
        {
          "name": "saturday",
          "display_order": 5,
          "display_names": {
            "en": "Saturday",
            "sv": "Lördag",
            "de": "Samstag"
          }
        },
        {
          "name": "sunday",
          "display_order": 6,
          "display_names": {
            "en": "Sunday",
            "sv": "Söndag",
            "de": "Sonntag"
          }
        }
      ],
      "study_text_intro": {
        "en": "This is our time use study for adults. Please reconstruct a typical week of your daily activities.",
        "sv": "Detta är vår tidsanvändningsstudie för vuxna. Vänligen återskapa en typisk vecka av dina dagliga aktiviteter.",
        "de": "Dies ist unsere Zeitnutzungsstudie für Erwachsene. Bitte rekonstruieren Sie eine typische Woche Ihrer täglichen Aktivitäten."
      },
      "study_text_end_completed": {
        "en": "Thanks for filling out this study. Your efforts will contribute to valuable research.",
        "sv": "Tack för att du fyllde i denna studie. Dina insatser kommer att bidra till värdefull forskning.",
        "de": "Vielen Dank für das Ausfüllen dieser Studie. Ihre Beiträge werden zu wertvoller Forschung beitragen."
      },
      "study_text_end_skipped": {
        "en": "You skipped the time reporting part. If you provided some information, we will try to use it. Thank you!",
        "sv": "Du hoppade över att fylla i tidsanvändningsdelen av studien. Om du har lämnat viss information kommer vi att försöka använda den. Tack!",
        "de": "Sie haben den Teil zur Zeitberichterstattung übersprungen. Wenn Sie einige Angaben gemacht haben, werden wir versuchen, diese zu verwenden. Vielen Dank!"
      },
      "require_consent": true,
      "is_paused": false,
      "study_text_consent": {
        "en": "# Study Consent Page\n\nBy continuing, you agree that:\n- your answers are collected for scientific time use research\n- the data may be analyzed in aggregated form\n- you can stop at any time before submitting",
        "sv": "# Sida för samtycke till studien\n\nGenom att fortsätta godkänner du att:\n- dina svar samlas in för vetenskaplig tidsanvändningsforskning\n- uppgifterna kan analyseras i samlad form\n- du kan avbryta när som helst innan du skickar in",
        "de": "# Einwilligungsseite für die Studie\n\nWenn Sie fortfahren, stimmen Sie zu, dass:\n- Ihre Antworten für wissenschaftliche Forschung zur Zeitnutzung erhoben werden\n- die Daten in zusammengefasster Form ausgewertet werden können\n- Sie jederzeit vor dem Absenden abbrechen können"
      },
      "study_text_end_noconsent": {
        "en": "You did not give consent and your data will not be used in this study.",
        "sv": "Du gav inte ditt samtycke och dina data kommer inte att användas i denna studie.",
        "de": "Sie haben keine Einwilligung gegeben und Ihre Daten werden in dieser Studie nicht verwendet."
      },
      "study_participant_ids": [],
      "allow_unlisted_participants": true,
      "default_language": "sv",
      "supported_languages": [
        "en", "sv", "de"
      ],
      "activities_json_files": {
        "en": "activities_ki_adults_en.json",
        "sv": "activities_ki_adults_sv.json",
        "de": "activities_ki_adults_de.json"
      },
      "data_collection_start": "2024-01-01T00:00:00Z",
      "data_collection_end": "2026-12-31T23:59:59Z"
    },
    {
      "name": "Weekly Study for 15 year olds",
      "name_short": "15yearolds",
      "description": "Weekly Study for 15 year olds at KI, filled out by themselves.",
      "day_labels": [
        {
          "name": "monday",
          "display_order": 0,
          "display_names": {
            "en": "Monday",
            "sv": "Måndag",
            "de": "Montag"
          }
        },
        {
          "name": "tuesday",
          "display_order": 1,
          "display_names": {
            "en": "Tuesday",
            "sv": "Tisdag",
            "de": "Dienstag"
          }
        },
        {
          "name": "wednesday",
          "display_order": 2,
          "display_names": {
            "en": "Wednesday",
            "sv": "Onsdag",
            "de": "Mittwoch"
          }
        },
        {
          "name": "thursday",
          "display_order": 3,
          "display_names": {
            "en": "Thursday",
            "sv": "Torsdag",
            "de": "Donnerstag"
          }
        },
        {
          "name": "friday",
          "display_order": 4,
          "display_names": {
            "en": "Friday",
            "sv": "Fredag",
            "de": "Freitag"
          }
        },
        {
          "name": "saturday",
          "display_order": 5,
          "display_names": {
            "en": "Saturday",
            "sv": "Lördag",
            "de": "Samstag"
          }
        },
        {
          "name": "sunday",
          "display_order": 6,
          "display_names": {
            "en": "Sunday",
            "sv": "Sunday",
            "de": "Sonntag"
          }
        }
      ],
      "study_text_intro": {
        "en": "This is our time use study for 15 year olds. Please reconstruct a typical week of your daily activities.",
        "sv": "Detta är vår tidsanvändningsstudie för 15-åringar. Vänligen återskapa en typisk vecka av dina dagliga aktiviteter.",
        "de": "Dies ist unsere Zeitnutzungsstudie für 15-Jährige. Bitte rekonstruieren Sie eine typische Woche Ihrer täglichen Aktivitäten."
      },
      "study_text_end_completed": {
        "en": "Thanks for filling out this study. Your efforts will contribute to valuable research.",
        "sv": "Tack för att du fyllde i denna studie. Dina insatser kommer att bidra till värdefull forskning.",
        "de": "Vielen Dank für das Ausfüllen dieser Studie. Ihre Beiträge werden zu wertvoller Forschung beitragen."
      },
      "study_text_end_skipped": {
        "en": "You skipped the time reporting part. If you provided some information, we will try to use it. Thank you!",
        "sv": "Du hoppade över att fylla i tidsanvändningsdelen av studien. Om du har lämnat viss information kommer vi att försöka använda den. Tack!",
        "de": "Sie haben den Teil zur Zeitberichterstattung übersprungen. Wenn Sie einige Angaben gemacht haben, werden wir versuchen, diese zu verwenden. Vielen Dank!"
      },
      "require_consent": true,
      "is_paused": false,
      "study_text_consent": {
        "en": "# Study Consent Page\n\nBy continuing, you agree that:\n- your answers are collected for scientific time use research\n- the data may be analyzed in aggregated form\n- you can stop at any time before submitting",
        "sv": "# Sida för samtycke till studien\n\nGenom att fortsätta godkänner du att:\n- dina svar samlas in för vetenskaplig tidsanvändningsforskning\n- uppgifterna kan analyseras i samlad form\n- du kan avbryta när som helst innan du skickar in",
        "de": "# Einwilligungsseite für die Studie\n\nWenn Sie fortfahren, stimmen Sie zu, dass:\n- Ihre Antworten für wissenschaftliche Forschung zur Zeitnutzung erhoben werden\n- die Daten in zusammengefasster Form ausgewertet werden können\n- Sie jederzeit vor dem Absenden abbrechen können"
      },
      "study_text_end_noconsent": {
        "en": "You did not give consent and your data will not be used in this study.",
        "sv": "Du gav inte ditt samtycke och dina data kommer inte att användas i denna studie.",
        "de": "Sie haben keine Einwilligung gegeben und Ihre Daten werden in dieser Studie nicht verwendet."
      },
      "study_participant_ids": [],
      "allow_unlisted_participants": true,
      "default_language": "en",
      "supported_languages": [
        "en",
        "sv", "de"
      ],
      "activities_json_files": {
        "en": "activities_ki_15yearolds_en.json",
        "sv": "activities_ki_15yearolds_sv.json",
        "de": "activities_ki_15yearolds_de.json"
      },
      "data_collection_start": "2024-01-01T00:00:00Z",
      "data_collection_end": "2026-12-31T23:59:59Z"
    },
    {
      "name": "Weekly Study for 9 year olds",
      "name_short": "9yearolds",
      "description": "Weekly Study for 9 year olds at KI, filled out by their parents.",
      "day_labels": [
        {
          "name": "monday",
          "display_order": 0,
          "display_names": {
            "en": "Monday",
            "sv": "Måndag",
            "de": "Montag"
          }
        },
        {
          "name": "tuesday",
          "display_order": 1,
          "display_names": {
            "en": "Tuesday",
            "sv": "Tisdag",
            "de": "Dienstag"
          }
        },
        {
          "name": "wednesday",
          "display_order": 2,
          "display_names": {
            "en": "Wednesday",
            "sv": "Onsdag",
            "de": "Mittwoch"
          }
        },
        {
          "name": "thursday",
          "display_order": 3,
          "display_names": {
            "en": "Thursday",
            "sv": "Torsdag",
            "de": "Donnerstag"
          }
        },
        {
          "name": "friday",
          "display_order": 4,
          "display_names": {
            "en": "Friday",
            "sv": "Fredag",
            "de": "Freitag"
          }
        },
        {
          "name": "friday",
          "display_order": 4,
          "display_names": {
            "en": "Friday",
            "sv": "Fredag",
            "de": "Freitag"
          }
        },
        {
          "name": "saturday",
          "display_order": 5,
          "display_names": {
            "en": "Saturday",
            "sv": "Lördag",
            "de": "Samstag"
          }
        },
        {
          "name": "sunday",
          "display_order": 6,
          "display_names": {
            "en": "Sunday",
            "sv": "Söndag",
            "de": "Sonntag"
          }
        }
      ],
      "study_text_intro": {
        "en": "Please fill out this study for 9 year old children. You will be asked to report time use for an entire week.",
        "sv": "Vänligen fyll i denna studie för 9-åringar. Du kommer att bli ombedd att rapportera tidsanvändning för en hel vecka.",
        "de": "Bitte füllen Sie diese Studie für 9-jährige Kinder aus. Sie werden gebeten, die Zeitnutzung für eine ganze Woche zu berichten."
      },
      "study_text_end_completed": {
        "en": "Thanks for filling out this study. Your efforts will contribute to valuable research.",
        "sv": "Tack för att du fyllde i denna studie. Dina insatser kommer att bidra till värdefull forskning.",
        "de": "Vielen Dank für das Ausfüllen dieser Studie. Ihre Beiträge werden zu wertvoller Forschung beitragen."
      },
      "study_text_end_skipped": {
        "en": "You have skipped filling out the time use part of the study. If you provided some information, we will try to use it. Thank you!",
        "sv": "Du har hoppat över att fylla i tidsanvändningsdelen av studien. Om du har lämnat viss information kommer vi att försöka använda den. Tack!",
        "de": "Sie haben das Ausfüllen des Zeitnutzungsteils der Studie übersprungen. Wenn Sie einige Angaben gemacht haben, werden wir versuchen, diese zu verwenden. Vielen Dank!"
      },
      "require_consent": true,
      "is_paused": false,
      "study_text_consent": {
        "en": "# Study Consent Page\n\nBy continuing, you agree that:\n- your answers are collected for scientific time use research\n- the data may be analyzed in aggregated form\n- you can stop at any time before submitting",
        "sv": "# Sida för samtycke till studien\n\nGenom att fortsätta godkänner du att:\n- dina svar samlas in för vetenskaplig tidsanvändningsforskning\n- uppgifterna kan analyseras i samlad form\n- du kan avbryta när som helst innan du skickar in",
        "de": "# Einwilligungsseite für die Studie\n\nWenn Sie fortfahren, stimmen Sie zu, dass:\n- Ihre Antworten für wissenschaftliche Forschung zur Zeitnutzung erhoben werden\n- die Daten in zusammengefasster Form ausgewertet werden können\n- Sie jederzeit vor dem Absenden abbrechen können"
      },
      "study_text_end_noconsent": {
        "en": "You did not give consent and your data will not be used in this study.",
        "sv": "Du gav inte ditt samtycke och dina data kommer inte att användas i denna studie.",
        "de": "Sie haben keine Einwilligung gegeben und Ihre Daten werden in dieser Studie nicht verwendet."
      },
      "study_participant_ids": [],
      "allow_unlisted_participants": true,
      "default_language": "sv",
      "supported_languages": [
        "en",
        "sv"
      ],
      "activities_json_files": {
        "en": "activities_ki_9yearolds_en.json",
        "sv": "activities_ki_9yearolds_sv.json",
        "de": "activities_ki_9yearolds_de.json"
      },
      "data_collection_start": "2024-01-01T00:00:00Z",
      "data_collection_end": "2026-12-31T23:59:59Z"
    }
  ]
}
